fc/__init__.py
fc/cloudtrailsdk/__init__.py
fc/cloudtrailsdk/execptions.py
fc/cloudtrailsdk/client/__init__.py
fc/cloudtrailsdk/client/tracker.py
fc/cloudtrailsdk/decorators/__init__.py
fc/cloudtrailsdk/decorators/api_gateway_tracker.py
fc/cloudtrailsdk/decorators/custom_tracker.py
fc/cloudtrailsdk/decorators/exception_tracker.py
fc/cloudtrailsdk/middleware/__init__.py
fc/cloudtrailsdk/model/__init__.py
fc/cloudtrailsdk/model/event.py
fc/cloudtrailsdk/utils/__init__.py
fc/cloudtrailsdk/utils/functions.py
tests/__init__.py
tests/conftest.py
tests/test_tracker.py
FIV_CloudTrails_SDK-2.0.1.dist-info/LICENSE.txt
FIV_CloudTrails_SDK-2.0.1.dist-info/METADATA
FIV_CloudTrails_SDK-2.0.1.dist-info/WHEEL
FIV_CloudTrails_SDK-2.0.1.dist-info/top_level.txt
FIV_CloudTrails_SDK-2.0.1.dist-info/RECORD
